CHANGELOG.rst
MANIFEST.in
README.rst
config-pg.yaml
config.yaml
docker-compose.yaml
integration_tests.py
setup.py
guillotina_hydraidp/__init__.py
guillotina_hydraidp/api.py
guillotina_hydraidp/events.py
guillotina_hydraidp/identifier.py
guillotina_hydraidp/interfaces.py
guillotina_hydraidp/json_definitions.py
guillotina_hydraidp/storage.py
guillotina_hydraidp/utils.py
guillotina_hydraidp.egg-info/PKG-INFO
guillotina_hydraidp.egg-info/SOURCES.txt
guillotina_hydraidp.egg-info/dependency_links.txt
guillotina_hydraidp.egg-info/requires.txt
guillotina_hydraidp.egg-info/top_level.txt
guillotina_hydraidp/tests/__init__.py
guillotina_hydraidp/tests/conftest.py
guillotina_hydraidp/tests/fixtures.py
guillotina_hydraidp/tests/test_users.py