Metadata-Version: 2.1
Name: guillotina-hydraidp
Version: 1.0.3
Summary: Guillotina based identity provider for hydra
Home-page: UNKNOWN
Author: Nathan Van Gheem
Author-email: vangheem@gmail.com
License: UNKNOWN
Platform: UNKNOWN
Provides-Extra: test
